LICENSE
README.md
setup.cfg
setup.py
petkitaio/__init__.py
petkitaio/constants.py
petkitaio/exceptions.py
petkitaio/model.py
petkitaio/petkit_client.py
petkitaio/str_enum.py
petkitaio.egg-info/PKG-INFO
petkitaio.egg-info/SOURCES.txt
petkitaio.egg-info/dependency_links.txt
petkitaio.egg-info/requires.txt
petkitaio.egg-info/top_level.txt