Metadata-Version: 2.1
Name: petkitaio
Version: 0.1.7
Summary: Asynchronous Python library for PetKit's API
Home-page: https://github.com/RobertD502/petkitaio
Author: Robert Drinovac
Author-email: unlisted@gmail.com
License: UNKNOWN
Project-URL: Bug Reports, https://github.com/RobertD502/petkitaio/issues
Project-URL: Source, https://github.com/RobertD502/petkitaio/
Keywords: petkit,eversweet 3 pro,feeder mini,d4,petkit feeder,petkit water fountain,freshelement solo,pura x,pura max,pura air
Platform: UNKNOWN
Classifier: Programming Language :: Python :: 3
Classifier: License :: OSI Approved :: MIT License
Classifier: Operating System :: OS Independent
Requires-Python: >=3.7
